dmtgen/__init__.py
dmtgen/base_generator.py
dmtgen/basic_template_generator.py
dmtgen/package_generator.py
dmtgen/template.py
dmtgen/template_generator.py
dmtgen/common/__init__.py
dmtgen/common/blueprint.py
dmtgen/common/blueprint_attribute.py
dmtgen/common/enum_description.py
dmtgen/common/package.py
dmtgen/common/system_package.py
dmtgen/data/system/SIMOS/entity.json
dmtgen/data/system/SIMOS/named_enity.json
tests/__init__.py
tests/test_relative_paths.py
dmtgen-0.4.2.dist-info/LICENSE
dmtgen-0.4.2.dist-info/METADATA
dmtgen-0.4.2.dist-info/WHEEL
dmtgen-0.4.2.dist-info/top_level.txt
dmtgen-0.4.2.dist-info/RECORD
