Metadata-Version: 2.1
Name: dmtgen
Version: 0.4.2
Summary: Python generator utilities for DMT
Home-page: UNKNOWN
Author: SINTEF Ocean
License: UNKNOWN
Platform: UNKNOWN
Classifier: Programming Language :: Python :: 3
Classifier: License :: OSI Approved :: MIT License
Classifier: Operating System :: OS Independent
Requires-Python: >=3.8
Requires-Dist: jinja2 (==3.0.2)
